daysgone/__init__.py
daysgone/__main__.py
daysgone-0.2.1.dist-info/entry_points.txt
daysgone-0.2.1.dist-info/LICENSE
daysgone-0.2.1.dist-info/WHEEL
daysgone-0.2.1.dist-info/METADATA
daysgone-0.2.1.dist-info/RECORD
