Metadata-Version: 2.1
Name: daysgone
Version: 0.2.1
Summary: Simple typer-cli app that will calculate days.
Home-page: https://github.com/mrcartoonster/daysgone
License: GPL-2.0-only
Author: Mr.Nobody
Author-email: mrcartoonster@yahoo.com
Requires-Python: >=3.9,<4.0
Classifier: License :: OSI Approved :: GNU General Public License v2 (GPLv2)
Classifier: Programming Language :: Python :: 3
Classifier: Programming Language :: Python :: 3.9
Requires-Dist: pendulum (>=2.1.2,<3.0.0)
Requires-Dist: rich (>=10.1.0,<11.0.0)
Requires-Dist: typer[all] (>=0.3.2,<0.4.0)
Project-URL: Repository, https://github.com/mrcartoonster/daysgone
